.coveragerc
.travis.yml
AUTHORS.rst
CHANGES.rst
LICENSE.txt
README.rst
requirements.txt
setup.cfg
setup.py
test-requirements.txt
datedown/__init__.py
datedown/dates.py
datedown/down.py
datedown/fname_creator.py
datedown/interface.py
datedown/urlcreator.py
datedown/wget.py
datedown.egg-info/PKG-INFO
datedown.egg-info/SOURCES.txt
datedown.egg-info/dependency_links.txt
datedown.egg-info/entry_points.txt
datedown.egg-info/not-zip-safe
datedown.egg-info/top_level.txt
docs/Makefile
docs/authors.rst
docs/changes.rst
docs/conf.py
docs/index.rst
docs/license.rst
docs/_static/.gitignore
tests/conftest.py
tests/test_dates.py
tests/test_down.py
tests/test_fnamecreator.py
tests/test_interface.py
tests/test_urlcreator.py
tests/test_data/year_month_subfolders/2000/01/file_2000_01_01.txt
tests/test_data/year_month_subfolders/2000/01/file_2000_01_02.txt
tests/test_data/year_month_subfolders/2000/02/file_2000_02_01.txt