Metadata-Version: 1.1
Name: datedown
Version: 0.3
Summary: Small library to download files with date and time based filenames or folder structures. In parallel using wget.
Home-page: https://github.com/cpaulik/datedown
Author: Christoph Paulik
Author-email: christoph.paulik@geo.tuwien.ac.at
License: mit
Platform: UNKNOWN
Classifier: Development Status :: 4 - Beta
Classifier: Programming Language :: Python
